ico_trade/__init__.py
ico_trade/contract/ICOContract.py
ico_trade/contract/ICOOption.py
ico_trade/contract/ICOStock.py
ico_trade/contract/__init__.py
ico_trade/core/ICOTrader.py
ico_trade/core/__init__.py
ico_trade/data_api/AbstractDataApi.py
ico_trade/data_api/IbApi.py
ico_trade/data_api/SqliteApi.py
ico_trade/data_api/__init__.py
ico_trade/indicator/BaseIndicator.py
ico_trade/indicator/DynamicIndicator.py
ico_trade/indicator/IndicatorFactory.py
ico_trade/indicator/StaticIndicator.py
ico_trade/indicator/__init__.py
ico_trade/objecs/enum.py
ico_trade/objecs/ICOBar.py
ico_trade/objecs/ICOTicker.py
ico_trade/objecs/__init__.py
ico_trade/util/date_util.py
ico_trade/util/__init__.py
ico_trade_core-0.0.1.dist-info/DESCRIPTION.rst
ico_trade_core-0.0.1.dist-info/METADATA
ico_trade_core-0.0.1.dist-info/metadata.json
ico_trade_core-0.0.1.dist-info/RECORD
ico_trade_core-0.0.1.dist-info/top_level.txt
ico_trade_core-0.0.1.dist-info/WHEEL
