Metadata-Version: 2.0
Name: ico-trade-core
Version: 0.0.1
Summary: 量化交易框架
Home-page: UNKNOWN
Author: hy
Author-email: UNKNOWN
License: UNKNOWN
Platform: UNKNOWN
